{
  "title": "Statistical Flowers for Algernon",
  "image": "https://www.smbc-comics.com/comics/1519242983-20180220.png",
  "hovertext": "I think there's a reading of Flowers for Algernon where the truth is he's just fundamentally a dickhead and everyone else who gets the same treatment fails to have an existential crisis.",
  "extra_image": "https://www.smbc-comics.com/comics/1519246498-20180220after.png",
  "url": "http://smbc-comics.com/comic/statistical-flowers-for-algernon",
  "prev": "https://www.smbc-comics.com/comic/the-truth",
  "next": "https://www.smbc-comics.com/comic/the-body"
}