{
  "title": "The Last Potion",
  "image": "https://www.smbc-comics.com/comics/1488037476-20170225.png",
  "hovertext": "Zach Weinersmith was known for his brilliant combinations of deep science, philosophy, mathematics, and literature.",
  "extra_image": "https://www.smbc-comics.com/comics/1488037462-20170225after.png",
  "url": "http://smbc-comics.com/comic/the-last-potion",
  "prev": "https://www.smbc-comics.com/comic/birth-strategy",
  "next": "https://www.smbc-comics.com/comic/teleporter-problems-2"
}