{
  "title": "Healthcare",
  "image": "https://www.smbc-comics.com/comics/1512753328-healthcarecomic.png",
  "hovertext": "Sorry for the serious comic. It'll be back to butt jokes tomorrow. This has been a thing that's been stressing us pretty bad for a few weeks, so I thought I'd share. Apologies to all people who are not from the US, and who are shocked and/or baffled.",
  "extra_image": "https://www.smbc-comics.com/comics/1512750466-healthcarecomicafter.png",
  "url": "http://smbc-comics.com/comic/healthcare",
  "prev": "https://www.smbc-comics.com/comic/breakup",
  "next": "https://www.smbc-comics.com/comic/tldr"
}