{
  "title": "The Real Supervillain",
  "image": "https://www.smbc-comics.com/comics/1517582562-20180202.png",
  "hovertext": "Thanks to the patreon typo squad for pointing out that the original version of this had given Bizarro the wrong skin tone. Nerds.",
  "extra_image": "https://www.smbc-comics.com/comics/1517582604-20180202after.png",
  "url": "http://smbc-comics.com/comic/the-real-supervillain",
  "prev": "https://www.smbc-comics.com/comic/the-future",
  "next": "https://www.smbc-comics.com/comic/self-assessment"
}